dummy_anndata/__init__.py
dummy_anndata/generate_dataframe.py
dummy_anndata/generate_dataset.py
dummy_anndata/generate_dict.py
dummy_anndata/generate_matrix.py
dummy_anndata/generate_vector.py
dummy_anndata-0.0.3.dist-info/METADATA
dummy_anndata-0.0.3.dist-info/WHEEL
dummy_anndata-0.0.3.dist-info/licenses/LICENSE
dummy_anndata-0.0.3.dist-info/RECORD
